{"openapi":"3.0.0","paths":{"/api/v1":{"get":{"operationId":"AppController_home","parameters":[],"responses":{"200":{"description":""}}}},"/api/v1/users":{"get":{"operationId":"UserController_getUsers","parameters":[],"responses":{"200":{"description":"","content":{"application/json":{"schema":{"type":"array","items":{"$ref":"#/components/schemas/User"}}}}}}}},"/api/v1/users/auth/signup":{"post":{"operationId":"UserController_signup","parameters":[],"requestBody":{"required":true,"content":{"application/json":{"schema":{"$ref":"#/components/schemas/CreateUserDto"}}}},"responses":{"201":{"description":"","content":{"application/json":{"schema":{"$ref":"#/components/schemas/SignupResponseDto"}}}}}}},"/api/v1/users/auth/signin":{"post":{"operationId":"UserController_signin","parameters":[],"requestBody":{"required":true,"content":{"application/json":{"schema":{"$ref":"#/components/schemas/AuthenticateUserDto"}}}},"responses":{"201":{"description":"","content":{"application/json":{"schema":{"$ref":"#/components/schemas/SigninResponseDto"}}}}}}},"/api/v1/users/auth/mail/check":{"post":{"operationId":"UserController_verifyEmail","parameters":[],"requestBody":{"required":true,"content":{"application/json":{"schema":{"$ref":"#/components/schemas/VerifyEmailDto"}}}},"responses":{"201":{"description":""}}}},"/api/v1/users/auth/check-email-existence/{email}":{"get":{"operationId":"UserController_checkIfEmailExists","parameters":[{"name":"email","required":true,"in":"path","schema":{"type":"string"}}],"responses":{"200":{"description":"","content":{"application/json":{"schema":{"type":"boolean"}}}}}}},"/api/v1/acccouts":{"get":{"operationId":"AccoutController_getAccounts","parameters":[],"responses":{"200":{"description":"","content":{"application/json":{"schema":{"type":"array","items":{"$ref":"#/components/schemas/Account"}}}}}}}},"/api/v1/acccouts/{code}":{"get":{"operationId":"AccoutController_getAccountOnlyById","parameters":[],"responses":{"200":{"description":"","content":{"application/json":{"schema":{"$ref":"#/components/schemas/Account"}}}}}}},"/api/v1/acccouts/create":{"post":{"operationId":"AccoutController_addAccount","parameters":[],"requestBody":{"required":true,"content":{"application/json":{"schema":{"$ref":"#/components/schemas/CreateAccountDto"}}}},"responses":{"201":{"description":"","content":{"application/json":{"schema":{"$ref":"#/components/schemas/Account"}}}}}}},"/api/v1/acccouts/update/{code}":{"put":{"operationId":"AccoutController_updateAccount","parameters":[],"requestBody":{"required":true,"content":{"application/json":{"schema":{"$ref":"#/components/schemas/updateAccountDto"}}}},"responses":{"200":{"description":""}}}},"/api/v1/acccouts/delete/{code}":{"delete":{"operationId":"AccoutController_deleteAccount","parameters":[],"responses":{"200":{"description":""}}}},"/api/v1/agents":{"get":{"operationId":"AgentController_getAgents","parameters":[],"responses":{"200":{"description":"","content":{"application/json":{"schema":{"type":"array","items":{"$ref":"#/components/schemas/Agent"}}}}}}}},"/api/v1/agents/{id}":{"get":{"operationId":"AgentController_getOnlyAgentById","parameters":[],"responses":{"200":{"description":"","content":{"application/json":{"schema":{"$ref":"#/components/schemas/Agent"}}}}}},"delete":{"operationId":"AgentController_deleteAgent","parameters":[],"responses":{"200":{"description":""}}}},"/api/v1/agents/create":{"post":{"operationId":"AgentController_createAgent","parameters":[],"requestBody":{"required":true,"content":{"application/json":{"schema":{"$ref":"#/components/schemas/CreateAgentDto"}}}},"responses":{"201":{"description":"","content":{"application/json":{"schema":{"$ref":"#/components/schemas/Agent"}}}}}}},"/api/v1/agents/update/{id}":{"put":{"operationId":"AgentController_UpdateAgentROle","parameters":[{"name":"id","required":true,"in":"path","schema":{"type":"number"}}],"requestBody":{"required":true,"content":{"application/json":{"schema":{"$ref":"#/components/schemas/updateAgentDto"}}}},"responses":{"200":{"description":"","content":{"application/json":{"schema":{"type":"object"}}}}}}},"/api/v1/agent-role":{"get":{"operationId":"AgentRoleController_getAgents","parameters":[],"responses":{"200":{"description":"","content":{"application/json":{"schema":{"type":"array","items":{"$ref":"#/components/schemas/AgentRole"}}}}}}}},"/api/v1/agent-role/{id}":{"get":{"operationId":"AgentRoleController_getOnlyAgentById","parameters":[],"responses":{"200":{"description":"","content":{"application/json":{"schema":{"$ref":"#/components/schemas/AgentRole"}}}}}},"delete":{"operationId":"AgentRoleController_deleteAgent","parameters":[],"responses":{"200":{"description":""}}}},"/api/v1/agent-role/create":{"post":{"operationId":"AgentRoleController_createAgentRole","parameters":[],"requestBody":{"required":true,"content":{"application/json":{"schema":{"$ref":"#/components/schemas/CreateAgentRoleDto"}}}},"responses":{"201":{"description":"","content":{"application/json":{"schema":{"$ref":"#/components/schemas/AgentRole"}}}}}}},"/api/v1/agent-role/update/{id}":{"put":{"operationId":"AgentRoleController_UpdateAgentROle","parameters":[{"name":"id","required":true,"in":"path","schema":{"type":"number"}}],"requestBody":{"required":true,"content":{"application/json":{"schema":{"$ref":"#/components/schemas/UpdateAgentRoleDto"}}}},"responses":{"200":{"description":"","content":{"application/json":{"schema":{"type":"object"}}}}}}},"/api/v1/carrers/create":{"post":{"operationId":"CareerController_createCarrer","parameters":[],"requestBody":{"required":true,"content":{"application/json":{"schema":{"$ref":"#/components/schemas/CreateCareerDto"}}}},"responses":{"201":{"description":"","content":{"application/json":{"schema":{"$ref":"#/components/schemas/Career"}}}}}}},"/api/v1/carrers":{"get":{"operationId":"CareerController_getAllCareer","parameters":[],"responses":{"200":{"description":"","content":{"application/json":{"schema":{"type":"array","items":{"$ref":"#/components/schemas/Career"}}}}}}}},"/api/v1/carrers/{id}":{"get":{"operationId":"CareerController_getCarrerById","parameters":[{"name":"id","required":true,"in":"path","schema":{"type":"number"}}],"responses":{"200":{"description":"","content":{"application/json":{"schema":{"$ref":"#/components/schemas/Career"}}}}}}},"/api/v1/carrers/update/{id}":{"put":{"operationId":"CareerController_updateAccount","parameters":[{"name":"id","required":true,"in":"path","schema":{"type":"number"}}],"requestBody":{"required":true,"content":{"application/json":{"schema":{"$ref":"#/components/schemas/UpdateCareerDto"}}}},"responses":{"200":{"description":"","content":{"application/json":{"schema":{"$ref":"#/components/schemas/Career"}}}}}}},"/api/v1/carrers/delete/{id}":{"delete":{"operationId":"CareerController_deleteAccount","parameters":[{"name":"id","required":true,"in":"path","schema":{"type":"number"}}],"responses":{"200":{"description":""}}}},"/api/v1/client-operation-type":{"get":{"operationId":"ClientOpationTypeController_getAllClientOperationType","parameters":[],"responses":{"200":{"description":"","content":{"application/json":{"schema":{"type":"array","items":{"$ref":"#/components/schemas/ClientOperationType"}}}}}}}},"/api/v1/client-operation-type/{id}":{"get":{"operationId":"ClientOpationTypeController_getOnlyClientOperationTypeById","parameters":[],"responses":{"200":{"description":"","content":{"application/json":{"schema":{"$ref":"#/components/schemas/ClientOperationType"}}}}}},"delete":{"operationId":"ClientOpationTypeController_deleteOpreaType","parameters":[{"name":"id","required":true,"in":"path","schema":{"type":"number"}}],"responses":{"200":{"description":""}}}},"/api/v1/client-operation-type/create":{"post":{"operationId":"ClientOpationTypeController_createOperaType","parameters":[],"requestBody":{"required":true,"content":{"application/json":{"schema":{"$ref":"#/components/schemas/CreateClientOperationTypeDto"}}}},"responses":{"201":{"description":"","content":{"application/json":{"schema":{"$ref":"#/components/schemas/ClientOperationType"}}}}}}},"/api/v1/client-operation-type/update/{id}":{"put":{"operationId":"ClientOpationTypeController_updateOperaType","parameters":[],"requestBody":{"required":true,"content":{"application/json":{"schema":{"$ref":"#/components/schemas/UpdateClientOperationTypeDto"}}}},"responses":{"200":{"description":"","content":{"application/json":{"schema":{"type":"object"}}}}}}},"/api/v1/compananies-categories/create":{"post":{"operationId":"CompanyCategoryController_createCarrer","parameters":[],"requestBody":{"required":true,"content":{"application/json":{"schema":{"$ref":"#/components/schemas/CreateCompanyCategory"}}}},"responses":{"201":{"description":"","content":{"application/json":{"schema":{"$ref":"#/components/schemas/CompanyCategory"}}}}}}},"/api/v1/compananies-categories":{"get":{"operationId":"CompanyCategoryController_getAllCompanyCategory","parameters":[],"responses":{"200":{"description":"","content":{"application/json":{"schema":{"type":"array","items":{"$ref":"#/components/schemas/CompanyCategory"}}}}}}}},"/api/v1/compananies-categories/{id}":{"get":{"operationId":"CompanyCategoryController_getCompanyCateById","parameters":[{"name":"id","required":true,"in":"path","schema":{"type":"number"}}],"responses":{"200":{"description":"","content":{"application/json":{"schema":{"$ref":"#/components/schemas/CompanyCategory"}}}}}}},"/api/v1/compananies-categories/update/{id}":{"put":{"operationId":"CompanyCategoryController_updateCompanyCate","parameters":[{"name":"id","required":true,"in":"path","schema":{"type":"number"}}],"requestBody":{"required":true,"content":{"application/json":{"schema":{"$ref":"#/components/schemas/UpdateCompanyCategoryDto"}}}},"responses":{"200":{"description":""}}}},"/api/v1/compananies-categories/delete/{id}":{"delete":{"operationId":"CompanyCategoryController_deleteCompanyCate","parameters":[{"name":"id","required":true,"in":"path","schema":{"type":"number"}}],"responses":{"200":{"description":""}}}},"/api/v1/companies/create":{"post":{"operationId":"CompanyController_createCompany","parameters":[],"requestBody":{"required":true,"content":{"application/json":{"schema":{"$ref":"#/components/schemas/CreateCompanyDto"}}}},"responses":{"201":{"description":"","content":{"application/json":{"schema":{"$ref":"#/components/schemas/Company"}}}}}}},"/api/v1/companies":{"get":{"operationId":"CompanyController_getAllCompany","parameters":[],"responses":{"200":{"description":"","content":{"application/json":{"schema":{"type":"array","items":{"$ref":"#/components/schemas/Company"}}}}}}}},"/api/v1/companies/{id}":{"get":{"operationId":"CompanyController_getCompanyById","parameters":[{"name":"id","required":true,"in":"path","schema":{"type":"number"}}],"responses":{"200":{"description":"","content":{"application/json":{"schema":{"$ref":"#/components/schemas/Company"}}}}}}},"/api/v1/companies/update/{id}":{"put":{"operationId":"CompanyController_updateCompany","parameters":[{"name":"id","required":true,"in":"path","schema":{"type":"number"}}],"requestBody":{"required":true,"content":{"application/json":{"schema":{"$ref":"#/components/schemas/UpdateCompanyDto"}}}},"responses":{"200":{"description":""}}}},"/api/v1/companies/delete/{id}":{"delete":{"operationId":"CompanyController_deleteCompany","parameters":[{"name":"id","required":true,"in":"path","schema":{"type":"number"}}],"responses":{"200":{"description":""}}}},"/api/v1/files/create":{"post":{"operationId":"FileController_createCarrer","parameters":[],"requestBody":{"required":true,"content":{"application/json":{"schema":{"$ref":"#/components/schemas/CreateFileDto"}}}},"responses":{"201":{"description":"","content":{"application/json":{"schema":{"$ref":"#/components/schemas/File"}}}}}}},"/api/v1/files":{"get":{"operationId":"FileController_getAllFile","parameters":[],"responses":{"200":{"description":"","content":{"application/json":{"schema":{"type":"array","items":{"$ref":"#/components/schemas/File"}}}}}}}},"/api/v1/files/{id}":{"get":{"operationId":"FileController_getFileById","parameters":[{"name":"id","required":true,"in":"path","schema":{"type":"number"}}],"responses":{"200":{"description":"","content":{"application/json":{"schema":{"$ref":"#/components/schemas/File"}}}}}}},"/api/v1/files/update/{id}":{"put":{"operationId":"FileController_updateAccount","parameters":[{"name":"id","required":true,"in":"path","schema":{"type":"number"}}],"requestBody":{"required":true,"content":{"application/json":{"schema":{"$ref":"#/components/schemas/UpdateFileDto"}}}},"responses":{"200":{"description":"","content":{"application/json":{"schema":{"$ref":"#/components/schemas/File"}}}}}}},"/api/v1/files/delete/{id}":{"delete":{"operationId":"FileController_deleteAccount","parameters":[{"name":"id","required":true,"in":"path","schema":{"type":"number"}}],"responses":{"200":{"description":""}}}},"/api/v1/licences/create":{"post":{"operationId":"LicenceController_create","parameters":[],"requestBody":{"required":true,"content":{"application/json":{"schema":{"$ref":"#/components/schemas/CreateLicenceDto"}}}},"responses":{"201":{"description":"","content":{"application/json":{"schema":{"type":"object"}}}}}}},"/api/v1/licences":{"get":{"operationId":"LicenceController_getAllLicence","parameters":[],"responses":{"200":{"description":"","content":{"application/json":{"schema":{"type":"array","items":{"$ref":"#/components/schemas/Licence"}}}}}}}},"/api/v1/licences/{id}":{"get":{"operationId":"LicenceController_gtLicenceById","parameters":[{"name":"id","required":true,"in":"path","schema":{"type":"number"}}],"responses":{"200":{"description":"","content":{"application/json":{"schema":{"$ref":"#/components/schemas/Licence"}}}}}}},"/api/v1/licences/update/{id}":{"put":{"operationId":"LicenceController_update","parameters":[{"name":"id","required":true,"in":"path","schema":{"type":"number"}}],"requestBody":{"required":true,"content":{"application/json":{"schema":{"$ref":"#/components/schemas/UpdateLicenceDto"}}}},"responses":{"200":{"description":"","content":{"application/json":{"schema":{"$ref":"#/components/schemas/Licence"}}}}}}},"/api/v1/licences/delete/{id}":{"delete":{"operationId":"LicenceController_delete","parameters":[{"name":"id","required":true,"in":"path","schema":{"type":"number"}}],"responses":{"200":{"description":""}}}},"/api/v1/operations-types/create":{"post":{"operationId":"OperationTypeController_create","parameters":[],"requestBody":{"required":true,"content":{"application/json":{"schema":{"$ref":"#/components/schemas/CreateOperationTypeDto"}}}},"responses":{"201":{"description":"","content":{"application/json":{"schema":{"type":"object"}}}}}}},"/api/v1/operations-types":{"get":{"operationId":"OperationTypeController_getAllOperationType","parameters":[],"responses":{"200":{"description":"","content":{"application/json":{"schema":{"type":"array","items":{"$ref":"#/components/schemas/OperationType"}}}}}}}},"/api/v1/operations-types/{id}":{"get":{"operationId":"OperationTypeController_getOperationTypeById","parameters":[{"name":"id","required":true,"in":"path","schema":{"type":"number"}}],"responses":{"200":{"description":"","content":{"application/json":{"schema":{"$ref":"#/components/schemas/OperationType"}}}}}}},"/api/v1/operations-types/update/{id}":{"put":{"operationId":"OperationTypeController_update","parameters":[{"name":"id","required":true,"in":"path","schema":{"type":"number"}}],"requestBody":{"required":true,"content":{"application/json":{"schema":{"$ref":"#/components/schemas/UpdateOperationTypeDto"}}}},"responses":{"200":{"description":""}}}},"/api/v1/operations-types/delete/{id}":{"delete":{"operationId":"OperationTypeController_delete","parameters":[{"name":"id","required":true,"in":"path","schema":{"type":"number"}}],"responses":{"200":{"description":""}}}},"/api/v1/operations/create":{"post":{"operationId":"OperationController_create","parameters":[],"requestBody":{"required":true,"content":{"application/json":{"schema":{"$ref":"#/components/schemas/CreateOperationDto"}}}},"responses":{"201":{"description":"","content":{"application/json":{"schema":{"$ref":"#/components/schemas/Operation"}}}}}}},"/api/v1/operations":{"get":{"operationId":"OperationController_getAll","parameters":[],"responses":{"200":{"description":"","content":{"application/json":{"schema":{"type":"array","items":{"$ref":"#/components/schemas/OperationType"}}}}}}}},"/api/v1/operations/{id}":{"get":{"operationId":"OperationController_getById","parameters":[{"name":"id","required":true,"in":"path","schema":{"type":"number"}}],"responses":{"200":{"description":"","content":{"application/json":{"schema":{"$ref":"#/components/schemas/OperationType"}}}}}}},"/api/v1/operations/update/{id}":{"put":{"operationId":"OperationController_update","parameters":[{"name":"id","required":true,"in":"path","schema":{"type":"number"}}],"requestBody":{"required":true,"content":{"application/json":{"schema":{"$ref":"#/components/schemas/UpdateOperationDto"}}}},"responses":{"200":{"description":"","content":{"application/json":{"schema":{"$ref":"#/components/schemas/Operation"}}}}}}},"/api/v1/operations/delete/{id}":{"delete":{"operationId":"OperationController_delete","parameters":[{"name":"id","required":true,"in":"path","schema":{"type":"number"}}],"responses":{"200":{"description":""}}}},"/api/v1/workfields/create":{"post":{"operationId":"WorkfieldController_create","parameters":[],"requestBody":{"required":true,"content":{"application/json":{"schema":{"$ref":"#/components/schemas/CreateWorkfieldDto"}}}},"responses":{"201":{"description":"","content":{"application/json":{"schema":{"$ref":"#/components/schemas/Workfield"}}}}}}},"/api/v1/workfields":{"get":{"operationId":"WorkfieldController_getAll","parameters":[],"responses":{"200":{"description":"","content":{"application/json":{"schema":{"type":"array","items":{"$ref":"#/components/schemas/Workfield"}}}}}}}},"/api/v1/workfields/{id}":{"get":{"operationId":"WorkfieldController_getById","parameters":[{"name":"id","required":true,"in":"path","schema":{"type":"number"}}],"responses":{"200":{"description":"","content":{"application/json":{"schema":{"$ref":"#/components/schemas/Workfield"}}}}}}},"/api/v1/workfields/update/{id}":{"put":{"operationId":"WorkfieldController_update","parameters":[{"name":"id","required":true,"in":"path","schema":{"type":"number"}}],"requestBody":{"required":true,"content":{"application/json":{"schema":{"$ref":"#/components/schemas/UpdateWorkfieldDto"}}}},"responses":{"200":{"description":""}}}},"/api/v1/workfields/delete/{id}":{"delete":{"operationId":"WorkfieldController_delete","parameters":[{"name":"id","required":true,"in":"path","schema":{"type":"number"}}],"responses":{"200":{"description":""}}}}},"info":{"title":"NUTITO SYSTEMS REST API","description":"This is the api for NUTITO SYSTEMS","version":"1.0","contact":{"name":"THE DEVCRAFT TEAM","url":"https://www.devcraft-team.com","email":"noreply@devcraft.com"}},"tags":[],"servers":[],"components":{"securitySchemes":{"bearer":{"scheme":"bearer","bearerFormat":"JWT","type":"http"}},"schemas":{"OperationType":{"type":"object","properties":{"name":{"type":"string"},"description":{"type":"string"},"type":{"type":"string"},"operations":{"type":"array","items":{"$ref":"#/components/schemas/Operation"}},"id":{"type":"number"},"created_at":{"format":"date-time","type":"string"},"updated_at":{"format":"date-time","type":"string"},"creator_id":{"type":"number"},"updater_id":{"type":"number"},"slug":{"type":"string"}},"required":["name","description","type","id","created_at","updated_at","creator_id","updater_id","slug"]},"ClientOperationType":{"type":"object","properties":{"name":{"type":"string"},"description":{"type":"string"},"type":{"type":"string"},"operations":{"type":"array","items":{"$ref":"#/components/schemas/Operation"}},"id":{"type":"number"},"created_at":{"format":"date-time","type":"string"},"updated_at":{"format":"date-time","type":"string"},"creator_id":{"type":"number"},"updater_id":{"type":"number"},"slug":{"type":"string"}},"required":["name","description","type","id","created_at","updated_at","creator_id","updater_id","slug"]},"Operation":{"type":"object","properties":{"name":{"type":"string"},"date":{"format":"date-time","type":"string"},"amount":{"type":"number"},"amount_in":{"type":"number"},"amount_out":{"type":"number"},"balance":{"type":"number"},"description":{"type":"string"},"documents":{"type":"array","items":{"$ref":"#/components/schemas/File"}},"operation_type":{"$ref":"#/components/schemas/OperationType"},"client_operation_type":{"$ref":"#/components/schemas/ClientOperationType"},"id":{"type":"number"},"created_at":{"format":"date-time","type":"string"},"updated_at":{"format":"date-time","type":"string"},"creator_id":{"type":"number"},"updater_id":{"type":"number"},"slug":{"type":"string"}},"required":["name","date","amount","amount_in","amount_out","balance","description","operation_type","client_operation_type","id","created_at","updated_at","creator_id","updater_id","slug"]},"User":{"type":"object","properties":{"id":{"type":"number"},"email":{"type":"string"},"phone":{"type":"string"},"ifu":{"type":"string"},"birth_date":{"format":"date-time","type":"string"},"birth_place":{"type":"string"},"address":{"type":"string"},"country":{"type":"string"},"password":{"type":"string"},"user_type":{"type":"string"},"verification_token":{"type":"string"},"active":{"type":"boolean"},"profile_pictures":{"type":"array","items":{"$ref":"#/components/schemas/File"}},"created_at":{"format":"date-time","type":"string"},"updated_at":{"format":"date-time","type":"string"},"creator_id":{"type":"number"},"updater_id":{"type":"number"},"slug":{"type":"string"}},"required":["id","email","phone","ifu","birth_date","birth_place","address","country","password","user_type","verification_token","active","created_at","updated_at","creator_id","updater_id","slug"]},"File":{"type":"object","properties":{"name":{"type":"string"},"location":{"type":"string"},"mimetype":{"type":"string"},"entity_id":{"type":"number"},"operation":{"$ref":"#/components/schemas/Operation"},"user":{"$ref":"#/components/schemas/User"},"id":{"type":"number"},"created_at":{"format":"date-time","type":"string"},"updated_at":{"format":"date-time","type":"string"},"creator_id":{"type":"number"},"updater_id":{"type":"number"},"slug":{"type":"string"}},"required":["name","location","mimetype","entity_id","operation","user","id","created_at","updated_at","creator_id","updater_id","slug"]},"CreateUserDto":{"type":"object","properties":{"email":{"type":"string"},"phone":{"type":"string"},"password":{"type":"string"},"user_type":{"type":"string"}},"required":["email","phone","password","user_type"]},"SignupResponseDto":{"type":"object","properties":{"message":{"type":"string"}},"required":["message"]},"AuthenticateUserDto":{"type":"object","properties":{"email":{"type":"string"},"password":{"type":"string"}},"required":["email","password"]},"SigninResponseDto":{"type":"object","properties":{"status":{"type":"string"},"access_token":{"type":"string"},"type":{"type":"string","default":"Bearer"}},"required":["status","access_token","type"]},"VerifyEmailDto":{"type":"object","properties":{"user":{"$ref":"#/components/schemas/CreateUserDto"},"token":{"type":"string"}},"required":["user","token"]},"Account":{"type":"object","properties":{"code":{"type":"string"},"amount":{"type":"number"},"amount_in":{"type":"number"},"amount_out":{"type":"number"},"id":{"type":"number"},"created_at":{"format":"date-time","type":"string"},"updated_at":{"format":"date-time","type":"string"},"creator_id":{"type":"number"},"updater_id":{"type":"number"},"slug":{"type":"string"}},"required":["code","amount","amount_in","amount_out","id","created_at","updated_at","creator_id","updater_id","slug"]},"CreateAccountDto":{"type":"object","properties":{"code":{"type":"string"},"amount":{"type":"number"},"amount_in":{"type":"number"},"amount_out":{"type":"number"}},"required":["code","amount","amount_in","amount_out"]},"updateAccountDto":{"type":"object","properties":{"code":{"type":"string"},"amount":{"type":"number"},"amount_in":{"type":"number"},"amount_out":{"type":"number"}}},"Agent":{"type":"object","properties":{"user":{"$ref":"#/components/schemas/User"},"careers":{"type":"array","items":{"$ref":"#/components/schemas/Career"}},"id":{"type":"number"},"created_at":{"format":"date-time","type":"string"},"updated_at":{"format":"date-time","type":"string"},"creator_id":{"type":"number"},"updater_id":{"type":"number"},"slug":{"type":"string"}},"required":["user","id","created_at","updated_at","creator_id","updater_id","slug"]},"CompanyCategory":{"type":"object","properties":{"name":{"type":"string"},"description":{"type":"string"},"companies":{"type":"array","items":{"$ref":"#/components/schemas/Company"}},"id":{"type":"number"},"created_at":{"format":"date-time","type":"string"},"updated_at":{"format":"date-time","type":"string"},"creator_id":{"type":"number"},"updater_id":{"type":"number"},"slug":{"type":"string"}},"required":["name","description","id","created_at","updated_at","creator_id","updater_id","slug"]},"Licence":{"type":"object","properties":{"expiry_date":{"format":"date-time","type":"string"},"amount":{"type":"number"},"code":{"type":"string"},"payment_type":{"type":"string"},"transaction_id":{"type":"number"},"transaction_info":{"type":"string"},"company":{"$ref":"#/components/schemas/Company"},"id":{"type":"number"},"created_at":{"format":"date-time","type":"string"},"updated_at":{"format":"date-time","type":"string"},"creator_id":{"type":"number"},"updater_id":{"type":"number"},"slug":{"type":"string"}},"required":["expiry_date","amount","code","payment_type","transaction_id","transaction_info","company","id","created_at","updated_at","creator_id","updater_id","slug"]},"Workfield":{"type":"object","properties":{"name":{"type":"string"},"description":{"type":"string"},"companies":{"type":"array","items":{"$ref":"#/components/schemas/Company"}},"id":{"type":"number"},"created_at":{"format":"date-time","type":"string"},"updated_at":{"format":"date-time","type":"string"},"creator_id":{"type":"number"},"updater_id":{"type":"number"},"slug":{"type":"string"}},"required":["name","description","id","created_at","updated_at","creator_id","updater_id","slug"]},"Company":{"type":"object","properties":{"name":{"type":"string"},"description":{"type":"string"},"city":{"type":"string"},"email":{"type":"string"},"phone":{"type":"string"},"address":{"type":"string"},"ifu":{"type":"string"},"rccm":{"type":"string"},"careers":{"type":"array","items":{"$ref":"#/components/schemas/Career"}},"category":{"$ref":"#/components/schemas/CompanyCategory"},"licences":{"type":"array","items":{"$ref":"#/components/schemas/Licence"}},"account":{"$ref":"#/components/schemas/Account"},"workfields":{"type":"array","items":{"$ref":"#/components/schemas/Workfield"}},"id":{"type":"number"},"created_at":{"format":"date-time","type":"string"},"updated_at":{"format":"date-time","type":"string"},"creator_id":{"type":"number"},"updater_id":{"type":"number"},"slug":{"type":"string"}},"required":["name","description","city","email","phone","address","ifu","rccm","category","account","id","created_at","updated_at","creator_id","updater_id","slug"]},"AgentRole":{"type":"object","properties":{"name":{"type":"string"},"description":{"type":"string"},"careers":{"type":"array","items":{"$ref":"#/components/schemas/Career"}},"id":{"type":"number"},"created_at":{"format":"date-time","type":"string"},"updated_at":{"format":"date-time","type":"string"},"creator_id":{"type":"number"},"updater_id":{"type":"number"},"slug":{"type":"string"}},"required":["name","description","id","created_at","updated_at","creator_id","updater_id","slug"]},"Career":{"type":"object","properties":{"agent":{"$ref":"#/components/schemas/Agent"},"company":{"$ref":"#/components/schemas/Company"},"role":{"$ref":"#/components/schemas/AgentRole"},"id":{"type":"number"},"created_at":{"format":"date-time","type":"string"},"updated_at":{"format":"date-time","type":"string"},"creator_id":{"type":"number"},"updater_id":{"type":"number"},"slug":{"type":"string"}},"required":["agent","company","role","id","created_at","updated_at","creator_id","updater_id","slug"]},"CreateAgentDto":{"type":"object","properties":{"user_id":{"type":"number"}},"required":["user_id"]},"updateAgentDto":{"type":"object","properties":{"user_id":{"type":"number"}}},"CreateAgentRoleDto":{"type":"object","properties":{"name":{"type":"string"},"description":{"type":"string"}},"required":["name","description"]},"UpdateAgentRoleDto":{"type":"object","properties":{"name":{"type":"string"},"description":{"type":"string"}}},"CreateCareerDto":{"type":"object","properties":{"agent":{"$ref":"#/components/schemas/Agent"},"company_id":{"type":"number"},"agent_role_id":{"type":"number"}},"required":["agent","company_id","agent_role_id"]},"UpdateCareerDto":{"type":"object","properties":{"agent_id":{"type":"number"},"company_id":{"type":"number"},"agent_role_id":{"type":"number"}}},"CreateClientOperationTypeDto":{"type":"object","properties":{"name":{"type":"string"},"description":{"type":"string"},"type":{"type":"string"}},"required":["name","description","type"]},"UpdateClientOperationTypeDto":{"type":"object","properties":{"name":{"type":"string"},"description":{"type":"string"},"type":{"type":"string"}}},"CreateCompanyCategory":{"type":"object","properties":{"name":{"type":"string"},"description":{"type":"string"}},"required":["name","description"]},"UpdateCompanyCategoryDto":{"type":"object","properties":{"name":{"type":"string"},"description":{"type":"string"}}},"CreateCompanyDto":{"type":"object","properties":{"name":{"type":"string"},"description":{"type":"string"},"city":{"type":"string"},"email":{"type":"string"},"phone":{"type":"string"},"adress":{"type":"string"},"ifu":{"type":"string"},"rccm":{"type":"string"},"company_category_id":{"type":"number"},"workfields":{"type":"array","items":{"type":"number"}}},"required":["name","description","city","email","phone","adress","ifu","rccm","company_category_id","workfields"]},"UpdateCompanyDto":{"type":"object","properties":{"name":{"type":"string"},"description":{"type":"string"},"city":{"type":"string"},"adress":{"type":"string"},"ifu":{"type":"string"},"rccm":{"type":"string"},"company_category_id":{"type":"number"},"companies_workfields":{"type":"number"}}},"CreateFileDto":{"type":"object","properties":{"name":{"type":"string"},"entity_id":{"type":"number"},"location":{"type":"string"},"mimetype":{"type":"string"},"operation_id":{"type":"number"},"user_id":{"type":"number"}},"required":["name","entity_id","location","mimetype","operation_id","user_id"]},"UpdateFileDto":{"type":"object","properties":{"name":{"type":"string"},"location":{"type":"string"},"mimetype":{"type":"string"},"entity_id":{"type":"number"},"operation_id":{"type":"number"},"user_id":{"type":"number"}}},"CreateLicenceDto":{"type":"object","properties":{"expiryDate":{"format":"date-time","type":"string"},"amount":{"type":"number"},"conde":{"type":"string"},"payement_type":{"type":"string"},"transaction_id":{"type":"number"},"transaction_info":{"type":"number"},"company_id":{"type":"number"}},"required":["expiryDate","amount","conde","payement_type","transaction_id","transaction_info","company_id"]},"UpdateLicenceDto":{"type":"object","properties":{"expiryDate":{"format":"date-time","type":"string"},"amount":{"type":"number"},"conde":{"type":"string"},"payement_type":{"type":"string"},"transaction_id":{"type":"number"},"transaction_info":{"type":"number"},"company_id":{"type":"number"}}},"CreateOperationTypeDto":{"type":"object","properties":{"name":{"type":"string"},"description":{"type":"string"},"type":{"type":"string"}},"required":["name","description","type"]},"UpdateOperationTypeDto":{"type":"object","properties":{"name":{"type":"string"},"description":{"type":"string"},"type":{"type":"string"}}},"CreateOperationDto":{"type":"object","properties":{"name":{"type":"string"},"date":{"format":"date-time","type":"string"},"amount_id":{"type":"number"},"balance":{"type":"number"},"description":{"type":"string"},"operation_type_id":{"type":"number"},"client_opration_type_id":{"type":"number"}},"required":["name","date","amount_id","balance","description","operation_type_id","client_opration_type_id"]},"UpdateOperationDto":{"type":"object","properties":{"name":{"type":"string"},"date":{"format":"date-time","type":"string"},"amount_id":{"type":"number"},"balance":{"type":"number"},"description":{"type":"string"},"operation_type_id":{"type":"number"},"client_opration_type_id":{"type":"number"}}},"CreateWorkfieldDto":{"type":"object","properties":{"name":{"type":"string"},"description":{"type":"string"}},"required":["name","description"]},"UpdateWorkfieldDto":{"type":"object","properties":{"name":{"type":"string"},"description":{"type":"string"}},"required":["name","description"]}}}}